{
  "data": {
    "staff": [
      {
        "name": "Andy",
        "flash": false,
        "image": "https://images.squarespace-cdn.com/content/v1/58b9484a59cc6856f3c58cf3/1602170749820-OGYKNEV4EXI95Q1FMLDE/AndyCummins.jpg?format=500w",
        "sound": "Andy.mp3",
        "daysWorked": ["Monday", "Tuesday", "Wednesday", "Thursday", "Friday"],
        "tech": false
      },
      {
        "name": "Alex",
        "flash": false,
        "image": "https://images.squarespace-cdn.com/content/v1/58b9484a59cc6856f3c58cf3/1488815272617-79VM1AF6S11NB7H85GL7/image-asset.jpeg?format=500w",
        "sound": "Alex.mp3",
        "daysWorked": ["Monday", "Tuesday", "Wednesday", "Thursday", "Friday"],
        "tech": false
      },
      {
        "name": "Arusha",
        "flash": false,
        "image": "https://ca.slack-edge.com/T045774MG-U05GXPLCTUY-3777ac15a132-512",
        "sound": "Arusha.mp3",
        "daysWorked": ["Monday", "Wednesday", "Thursday"],
        "tech": false
      },
      {
        "name": "Ben",
        "flash": false,
        "image": "https://images.squarespace-cdn.com/content/v1/58b9484a59cc6856f3c58cf3/1521128137044-DOCW62GKT5OFS4ZBNR0Y/ben-small-1.jpg?format=500w",
        "sound": "Ben.mp3",
        "daysWorked": ["Monday", "Tuesday", "Wednesday", "Thursday", "Friday"],
        "tech": false
      },
      {
        "name": "Emily",
        "flash": false,
        "image": "https://images.squarespace-cdn.com/content/v1/58b9484a59cc6856f3c58cf3/1591020543497-BBTKJDIQKCKNDCV782CM/emily3edit.jpg?format=500w",
        "sound": "Emily.mp3",
        "daysWorked": ["Monday", "Tuesday", "Wednesday", "Thursday", "Friday"],
        "tech": true
      },
      {
        "name": "Grant",
        "flash": false,
        "image": "https://images.squarespace-cdn.com/content/v1/58b9484a59cc6856f3c58cf3/1521125495521-MUEUA0WH2KLZL0DLD895/grant-small-2.jpg?format=500w",
        "sound": "Grant.mp3",
        "daysWorked": ["Tuesday", "Wednesday", "Thursday", "Friday"],
        "tech": false
      },
      {
        "name": "Hannah",
        "flash": false,
        "image": "https://images.squarespace-cdn.com/content/v1/58b9484a59cc6856f3c58cf3/9e91d44b-fd6a-4a18-8e6e-8f35ea8e1e3d/HannahB.jpg?format=500w",
        "sound": "Hannah.mp3",
        "daysWorked": ["Monday", "Tuesday", "Wednesday", "Thursday", "Friday"],
        "tech": true
      },
      {
        "name": "Iain",
        "flash": false,
        "image": "https://images.squarespace-cdn.com/content/v1/58b9484a59cc6856f3c58cf3/1610975738054-XPGU8306ZJKLPVFTPGZI/me.jpg?format=500w",
        "sound": "Iain.mp3",
        "daysWorked": ["Monday", "Tuesday", "Wednesday", "Thursday", "Friday"],
        "tech": true
      },
      {
        "name": "James",
        "flash": false,
        "image": "https://images.squarespace-cdn.com/content/v1/58b9484a59cc6856f3c58cf3/1560775570386-VOFV4X5XF4P6Y3SQU2J1/Image+from+iOS+%281%29.jpg?format=500w",
        "sound": "James.mp3",
        "daysWorked": ["Monday", "Tuesday", "Wednesday", "Thursday", "Friday"],
        "tech": true
      },
      {
        "name": "Jon",
        "flash": false,
        "image": "https://images.squarespace-cdn.com/content/v1/58b9484a59cc6856f3c58cf3/1521818417633-0ESQX8911EEHZEJ50D41/ca-1.jpg?format=500w",
        "sound": "Jon.mp3",
        "daysWorked": ["Monday", "Tuesday", "Wednesday", "Thursday", "Friday"],
        "tech": true
      },
      {
        "name": "Luke",
        "flash": false,
        "image": "https://images.squarespace-cdn.com/content/v1/58b9484a59cc6856f3c58cf3/1615915089110-KDK5MVZTW2TPL78A0VHF/lukewd.jpg?format=500w",
        "sound": "Luke.mp3",
        "daysWorked": ["Monday", "Tuesday", "Wednesday", "Thursday", "Friday"],
        "tech": false
      },
      {
        "name": "Lou",
        "flash": false,
        "image": "https://ladiesthatux.com/wp-content/uploads/2023/01/Lou_2023-2048x2048.jpg",
        "sound": "Lou.mp3",
        "daysWorked": ["Monday", "Wednesday", "Friday"],
        "tech": false
      },
      {
        "name": "Matt",
        "flash": false,
        "image": "https://images.squarespace-cdn.com/content/v1/58b9484a59cc6856f3c58cf3/1591012058042-HRMWKIU1NWNXMURG2SLV/IMG_0399.jpg?format=500w",
        "sound": "Matt.mp3",
        "daysWorked": ["Monday", "Tuesday", "Wednesday", "Thursday", "Friday"],
        "tech": true
      },
      {
        "name": "Neil",
        "flash": false,
        "image": "https://images.squarespace-cdn.com/content/v1/58b9484a59cc6856f3c58cf3/1521818512674-LSF0MJGLL5DA28CEGW7R/ca-7.jpg?format=500w",
        "sound": "Neil.mp3",
        "daysWorked": ["Monday", "Tuesday", "Wednesday", "Thursday", "Friday"],
        "tech": true
      },
      {
        "name": "Nick",
        "flash": false,
        "image": "https://cogapp-website-files-prod.s3.eu-west-2.amazonaws.com/Team-photos/_432x432_crop_center-center_none/NickC.jpg",
        "sound": "Nick.mp3",
        "daysWorked": ["Monday", "Tuesday", "Wednesday", "Thursday", "Friday"],
        "tech": false
      },
      {
        "name": "Nitin",
        "flash": false,
        "image": "https://ca.slack-edge.com/T045774MG-U02KE3ZM5LY-6a3476e26248-512",
        "sound": "Nitin.mp3",
        "daysWorked": ["Monday", "Tuesday", "Wednesday", "Thursday", "Friday"],
        "tech": true
      },
      {
        "name": "Scout",
        "flash": false,
        "image": "https://images.squarespace-cdn.com/content/v1/58b9484a59cc6856f3c58cf3/1574091028333-SEDTF04PLLH5JBTUXFL4/Image+from+iOS+%282%29.jpg?format=500w",
        "sound": "Scout.mp3",
        "daysWorked": ["Monday", "Tuesday", "Wednesday", "Thursday", "Friday"],
        "tech": false
      },
      {
        "name": "Steve",
        "flash": false,
        "image": "https://images.squarespace-cdn.com/content/v1/58b9484a59cc6856f3c58cf3/1488815669959-GGX5VVLTXYWH96BARUST/image-asset.png?format=500w",
        "sound": "Steve.mp3",
        "daysWorked": ["Monday", "Tuesday", "Wednesday", "Thursday", "Friday"],
        "tech": true
      },
      {
        "name": "Tristan",
        "flash": false,
        "image": "https://images.squarespace-cdn.com/content/v1/58b9484a59cc6856f3c58cf3/1516702449445-HM18UV7Y944SP3WNYA8O/20180117-IMG_7520.jpg?format=500w",
        "sound": "Tristan.mp3",
        "daysWorked": ["Monday", "Tuesday", "Wednesday", "Thursday", "Friday"],
        "tech": true
      }
    ]
  }
}
